latexpkges3.py
latexpkges3-1.0.dist-info/LICENSE
latexpkges3-1.0.dist-info/METADATA
latexpkges3-1.0.dist-info/WHEEL
latexpkges3-1.0.dist-info/entry_points.txt
latexpkges3-1.0.dist-info/top_level.txt
latexpkges3-1.0.dist-info/RECORD
