Metadata-Version: 2.1
Name: latexpkges3
Version: 1.0
Summary: utility for cleaning unused LaTeX packages
Home-page: https://github.com/TarasKuzyo/LaTeXpkges
Author: Taras Kuzyo
Author-email: kuzyo.taras@gmail.com
License: MIT
Keywords: tools cleanup LaTeX
Platform: UNKNOWN
Classifier: Development Status :: 5 - Production/Stable
Classifier: Intended Audience :: Developers
Classifier: License :: OSI Approved :: MIT License
Classifier: Programming Language :: Python
Classifier: Programming Language :: Python :: 3
Classifier: Programming Language :: Python :: 3.5
Classifier: Programming Language :: Python :: 3.6
Classifier: Programming Language :: Python :: 3.7
Classifier: Programming Language :: Python :: 3.8
Classifier: Programming Language :: Python :: 3.9
Requires-Python: >=3.5
License-File: LICENSE
